{"nodes": [{"id": "workflows_release_release_workflow", "label": "Release Workflow", "file_type": "code", "source_file": ".github/workflows/release.yml", "source_location": "lines 1-82", "source_url": null, "captured_at": null, "author": null, "contributor": null}, {"id": "workflows_release_tag_triggered_release", "label": "Tag-Triggered Release", "file_type": "concept", "source_file": ".github/workflows/release.yml", "source_location": "lines 3-5", "source_url": null, "captured_at": null, "author": null, "contributor": null}, {"id": "workflows_release_build_job", "label": "Cross-Platform Build Job", "file_type": "code", "source_file": ".github/workflows/release.yml", "source_location": "lines 11-47", "source_url": null, "captured_at": null, "author": null, "contributor": null}, {"id": "workflows_release_artifact_attestation", "label": "GitHub Artifact Attestation", "file_type": "concept", "source_file": ".github/workflows/release.yml", "source_location": "lines 39-42", "source_url": null, "captured_at": null, "author": null, "contributor": null}, {"id": "workflows_release_publish_job", "label": "Release Publish Job", "file_type": "code", "source_file": ".github/workflows/release.yml", "source_location": "lines 49-82", "source_url": null, "captured_at": null, "author": null, "contributor": null}, {"id": "workflows_release_sha256_checksums", "label": "SHA-256 Release Checksums", "file_type": "concept", "source_file": ".github/workflows/release.yml", "source_location": "lines 64-66", "source_url": null, "captured_at": null, "author": null, "contributor": null}, {"id": "workflows_release_github_release_publication", "label": "GitHub Release Publication", "file_type": "concept", "source_file": ".github/workflows/release.yml", "source_location": "lines 67-82", "source_url": null, "captured_at": null, "author": null, "contributor": null}], "edges": [{"source": "workflows_release_release_workflow", "target": "workflows_release_tag_triggered_release", "relation": "implements", "confidence": "EXTRACTED", "confidence_score": 1.0, "source_file": ".github/workflows/release.yml", "source_location": "lines 3-5", "weight": 1.0}, {"source": "workflows_release_release_workflow", "target": "workflows_release_build_job", "relation": "implements", "confidence": "EXTRACTED", "confidence_score": 1.0, "source_file": ".github/workflows/release.yml", "source_location": "lines 10-47", "weight": 1.0}, {"source": "workflows_release_release_workflow", "target": "workflows_release_publish_job", "relation": "implements", "confidence": "EXTRACTED", "confidence_score": 1.0, "source_file": ".github/workflows/release.yml", "source_location": "lines 49-82", "weight": 1.0}, {"source": "workflows_release_build_job", "target": "workflows_release_artifact_attestation", "relation": "implements", "confidence": "EXTRACTED", "confidence_score": 1.0, "source_file": ".github/workflows/release.yml", "source_location": "lines 39-42", "weight": 1.0}, {"source": "workflows_release_publish_job", "target": "workflows_release_build_job", "relation": "references", "confidence": "EXTRACTED", "confidence_score": 1.0, "source_file": ".github/workflows/release.yml", "source_location": "line 50", "weight": 1.0}, {"source": "workflows_release_publish_job", "target": "workflows_release_sha256_checksums", "relation": "implements", "confidence": "EXTRACTED", "confidence_score": 1.0, "source_file": ".github/workflows/release.yml", "source_location": "lines 64-66", "weight": 1.0}, {"source": "workflows_release_publish_job", "target": "workflows_release_github_release_publication", "relation": "implements", "confidence": "EXTRACTED", "confidence_score": 1.0, "source_file": ".github/workflows/release.yml", "source_location": "lines 67-82", "weight": 1.0}, {"source": "workflows_release_sha256_checksums", "target": "workflows_release_github_release_publication", "relation": "shares_data_with", "confidence": "EXTRACTED", "confidence_score": 1.0, "source_file": ".github/workflows/release.yml", "source_location": "lines 64-77", "weight": 1.0}], "hyperedges": [{"id": "release_supply_chain_verification", "label": "Release Supply-Chain Verification", "nodes": ["workflows_release_artifact_attestation", "workflows_release_sha256_checksums", "workflows_release_github_release_publication", "readme_release_provenance_verification", "security_fail_closed_update_verification"], "relation": "participate_in", "confidence": "INFERRED", "confidence_score": 0.95, "source_file": ".github/workflows/release.yml"}]}