{"nodes": [{"id": "users_phranck_developer_tools_cli_grat_internal_settings_settings_go", "label": "settings.go", "file_type": "code", "source_file": "internal/settings/settings.go", "source_location": "L1"}, {"id": "settings_settings", "label": "Settings", "file_type": "code", "source_file": "internal/settings/settings.go", "source_location": "L24"}, {"id": "settings_store", "label": "Store", "file_type": "code", "source_file": "internal/settings/settings.go", "source_location": "L31"}, {"id": "settings_settings_configdirectory", "label": "ConfigDirectory()", "file_type": "code", "source_file": "internal/settings/settings.go", "source_location": "L39"}, {"id": "settings_store_path", "label": ".Path()", "file_type": "code", "source_file": "internal/settings/settings.go", "source_location": "L48"}, {"id": "settings_store_load", "label": ".Load()", "file_type": "code", "source_file": "internal/settings/settings.go", "source_location": "L58"}, {"id": "settings_store_save", "label": ".Save()", "file_type": "code", "source_file": "internal/settings/settings.go", "source_location": "L81"}, {"id": "settings_store_add", "label": ".Add()", "file_type": "code", "source_file": "internal/settings/settings.go", "source_location": "L132"}, {"id": "settings_store_remove", "label": ".Remove()", "file_type": "code", "source_file": "internal/settings/settings.go", "source_location": "L159"}, {"id": "settings_store_normalize", "label": ".Normalize()", "file_type": "code", "source_file": "internal/settings/settings.go", "source_location": "L191"}, {"id": "settings_store_defaultdirectory", "label": ".DefaultDirectory()", "file_type": "code", "source_file": "internal/settings/settings.go", "source_location": "L230"}, {"id": "settings_settings_contains", "label": "Contains()", "file_type": "code", "source_file": "internal/settings/settings.go", "source_location": "L245"}, {"id": "settings_store_validate", "label": ".validate()", "file_type": "code", "source_file": "internal/settings/settings.go", "source_location": "L261"}, {"id": "settings_store_canonicalize", "label": ".canonicalize()", "file_type": "code", "source_file": "internal/settings/settings.go", "source_location": "L288"}, {"id": "settings_settings_canonicalexistingpath", "label": "canonicalExistingPath()", "file_type": "code", "source_file": "internal/settings/settings.go", "source_location": "L304"}, {"id": "settings_settings_canonicalexistingdirectory", "label": "canonicalExistingDirectory()", "file_type": "code", "source_file": "internal/settings/settings.go", "source_location": "L319"}, {"id": "settings_store_configdirectory", "label": ".configDirectory()", "file_type": "code", "source_file": "internal/settings/settings.go", "source_location": "L334"}, {"id": "settings_store_homedirectory", "label": ".homeDirectory()", "file_type": "code", "source_file": "internal/settings/settings.go", "source_location": "L341"}, {"id": "settings_store_workingdirectory", "label": ".workingDirectory()", "file_type": "code", "source_file": "internal/settings/settings.go", "source_location": "L352"}, {"id": "settings_store_rename", "label": ".rename()", "file_type": "code", "source_file": "internal/settings/settings.go", "source_location": "L363"}], "edges": [{"source": "users_phranck_developer_tools_cli_grat_internal_settings_settings_go", "target": "go_pkg_bytes", "relation": "imports_from", "confidence": "EXTRACTED", "source_file": "internal/settings/settings.go", "source_location": "L5", "weight": 1.0, "context": "import"}, {"source": "users_phranck_developer_tools_cli_grat_internal_settings_settings_go", "target": "go_pkg_errors", "relation": "imports_from", "confidence": "EXTRACTED", "source_file": "internal/settings/settings.go", "source_location": "L6", "weight": 1.0, "context": "import"}, {"source": "users_phranck_developer_tools_cli_grat_internal_settings_settings_go", "target": "go_pkg_fmt", "relation": "imports_from", "confidence": "EXTRACTED", "source_file": "internal/settings/settings.go", "source_location": "L7", "weight": 1.0, "context": "import"}, {"source": "users_phranck_developer_tools_cli_grat_internal_settings_settings_go", "target": "go_pkg_os", "relation": "imports_from", "confidence": "EXTRACTED", "source_file": "internal/settings/settings.go", "source_location": "L8", "weight": 1.0, "context": "import"}, {"source": "users_phranck_developer_tools_cli_grat_internal_settings_settings_go", "target": "go_pkg_path_filepath", "relation": "imports_from", "confidence": "EXTRACTED", "source_file": "internal/settings/settings.go", "source_location": "L9", "weight": 1.0, "context": "import"}, {"source": "users_phranck_developer_tools_cli_grat_internal_settings_settings_go", "target": "go_pkg_sort", "relation": "imports_from", "confidence": "EXTRACTED", "source_file": "internal/settings/settings.go", "source_location": "L10", "weight": 1.0, "context": "import"}, {"source": "users_phranck_developer_tools_cli_grat_internal_settings_settings_go", "target": "go_pkg_strings", "relation": "imports_from", "confidence": "EXTRACTED", "source_file": "internal/settings/settings.go", "source_location": "L11", "weight": 1.0, "context": "import"}, {"source": "users_phranck_developer_tools_cli_grat_internal_settings_settings_go", "target": "go_pkg_github_com_pelletier_go_toml_v2", "relation": "imports_from", "confidence": "EXTRACTED", "source_file": "internal/settings/settings.go", "source_location": "L13", "weight": 1.0, "context": "import"}, {"source": "users_phranck_developer_tools_cli_grat_internal_settings_settings_go", "target": "settings_settings", "relation": "contains", "confidence": "EXTRACTED", "source_file": "internal/settings/settings.go", "source_location": "L24", "weight": 1.0}, {"source": "users_phranck_developer_tools_cli_grat_internal_settings_settings_go", "target": "settings_store", "relation": "contains", "confidence": "EXTRACTED", "source_file": "internal/settings/settings.go", "source_location": "L31", "weight": 1.0}, {"source": "users_phranck_developer_tools_cli_grat_internal_settings_settings_go", "target": "settings_settings_configdirectory", "relation": "contains", "confidence": "EXTRACTED", "source_file": "internal/settings/settings.go", "source_location": "L39", "weight": 1.0}, {"source": "settings_store", "target": "settings_store_path", "relation": "method", "confidence": "EXTRACTED", "source_file": "internal/settings/settings.go", "source_location": "L48", "weight": 1.0}, {"source": "settings_store", "target": "settings_store_load", "relation": "method", "confidence": "EXTRACTED", "source_file": "internal/settings/settings.go", "source_location": "L58", "weight": 1.0}, {"source": "settings_store_load", "target": "settings_settings", "relation": "references", "confidence": "EXTRACTED", "source_file": "internal/settings/settings.go", "source_location": "L58", "weight": 1.0, "context": "return_type"}, {"source": "settings_store", "target": "settings_store_save", "relation": "method", "confidence": "EXTRACTED", "source_file": "internal/settings/settings.go", "source_location": "L81", "weight": 1.0}, {"source": "settings_store_save", "target": "settings_settings", "relation": "references", "confidence": "EXTRACTED", "source_file": "internal/settings/settings.go", "source_location": "L81", "weight": 1.0, "context": "parameter_type"}, {"source": "settings_store", "target": "settings_store_add", "relation": "method", "confidence": "EXTRACTED", "source_file": "internal/settings/settings.go", "source_location": "L132", "weight": 1.0}, {"source": "settings_store_add", "target": "settings_settings", "relation": "references", "confidence": "EXTRACTED", "source_file": "internal/settings/settings.go", "source_location": "L132", "weight": 1.0, "context": "return_type"}, {"source": "settings_store", "target": "settings_store_remove", "relation": "method", "confidence": "EXTRACTED", "source_file": "internal/settings/settings.go", "source_location": "L159", "weight": 1.0}, {"source": "settings_store_remove", "target": "settings_settings", "relation": "references", "confidence": "EXTRACTED", "source_file": "internal/settings/settings.go", "source_location": "L159", "weight": 1.0, "context": "return_type"}, {"source": "settings_store", "target": "settings_store_normalize", "relation": "method", "confidence": "EXTRACTED", "source_file": "internal/settings/settings.go", "source_location": "L191", "weight": 1.0}, {"source": "settings_store", "target": "settings_store_defaultdirectory", "relation": "method", "confidence": "EXTRACTED", "source_file": "internal/settings/settings.go", "source_location": "L230", "weight": 1.0}, {"source": "users_phranck_developer_tools_cli_grat_internal_settings_settings_go", "target": "settings_settings_contains", "relation": "contains", "confidence": "EXTRACTED", "source_file": "internal/settings/settings.go", "source_location": "L245", "weight": 1.0}, {"source": "settings_store", "target": "settings_store_validate", "relation": "method", "confidence": "EXTRACTED", "source_file": "internal/settings/settings.go", "source_location": "L261", "weight": 1.0}, {"source": "settings_store_validate", "target": "settings_settings", "relation": "references", "confidence": "EXTRACTED", "source_file": "internal/settings/settings.go", "source_location": "L261", "weight": 1.0, "context": "parameter_type"}, {"source": "settings_store", "target": "settings_store_canonicalize", "relation": "method", "confidence": "EXTRACTED", "source_file": "internal/settings/settings.go", "source_location": "L288", "weight": 1.0}, {"source": "settings_store_canonicalize", "target": "settings_settings", "relation": "references", "confidence": "EXTRACTED", "source_file": "internal/settings/settings.go", "source_location": "L288", "weight": 1.0, "context": "parameter_type"}, {"source": "settings_store_canonicalize", "target": "settings_settings", "relation": "references", "confidence": "EXTRACTED", "source_file": "internal/settings/settings.go", "source_location": "L288", "weight": 1.0, "context": "return_type"}, {"source": "users_phranck_developer_tools_cli_grat_internal_settings_settings_go", "target": "settings_settings_canonicalexistingpath", "relation": "contains", "confidence": "EXTRACTED", "source_file": "internal/settings/settings.go", "source_location": "L304", "weight": 1.0}, {"source": "users_phranck_developer_tools_cli_grat_internal_settings_settings_go", "target": "settings_settings_canonicalexistingdirectory", "relation": "contains", "confidence": "EXTRACTED", "source_file": "internal/settings/settings.go", "source_location": "L319", "weight": 1.0}, {"source": "settings_store", "target": "settings_store_configdirectory", "relation": "method", "confidence": "EXTRACTED", "source_file": "internal/settings/settings.go", "source_location": "L334", "weight": 1.0}, {"source": "settings_store", "target": "settings_store_homedirectory", "relation": "method", "confidence": "EXTRACTED", "source_file": "internal/settings/settings.go", "source_location": "L341", "weight": 1.0}, {"source": "settings_store", "target": "settings_store_workingdirectory", "relation": "method", "confidence": "EXTRACTED", "source_file": "internal/settings/settings.go", "source_location": "L352", "weight": 1.0}, {"source": "settings_store", "target": "settings_store_rename", "relation": "method", "confidence": "EXTRACTED", "source_file": "internal/settings/settings.go", "source_location": "L363", "weight": 1.0}, {"source": "settings_store_path", "target": "settings_store_configdirectory", "relation": "calls", "context": "call", "confidence": "EXTRACTED", "source_file": "internal/settings/settings.go", "source_location": "L49", "weight": 1.0}, {"source": "settings_store_load", "target": "settings_store_path", "relation": "calls", "context": "call", "confidence": "EXTRACTED", "source_file": "internal/settings/settings.go", "source_location": "L59", "weight": 1.0}, {"source": "settings_store_load", "target": "settings_store_validate", "relation": "calls", "context": "call", "confidence": "EXTRACTED", "source_file": "internal/settings/settings.go", "source_location": "L74", "weight": 1.0}, {"source": "settings_store_save", "target": "settings_store_canonicalize", "relation": "calls", "context": "call", "confidence": "EXTRACTED", "source_file": "internal/settings/settings.go", "source_location": "L83", "weight": 1.0}, {"source": "settings_store_save", "target": "settings_store_validate", "relation": "calls", "context": "call", "confidence": "EXTRACTED", "source_file": "internal/settings/settings.go", "source_location": "L87", "weight": 1.0}, {"source": "settings_store_save", "target": "settings_store_path", "relation": "calls", "context": "call", "confidence": "EXTRACTED", "source_file": "internal/settings/settings.go", "source_location": "L90", "weight": 1.0}, {"source": "settings_store_save", "target": "settings_store_remove", "relation": "calls", "context": "call", "confidence": "EXTRACTED", "source_file": "internal/settings/settings.go", "source_location": "L112", "weight": 1.0}, {"source": "settings_store_save", "target": "settings_store_rename", "relation": "calls", "context": "call", "confidence": "EXTRACTED", "source_file": "internal/settings/settings.go", "source_location": "L125", "weight": 1.0}, {"source": "settings_store_add", "target": "settings_store_normalize", "relation": "calls", "context": "call", "confidence": "EXTRACTED", "source_file": "internal/settings/settings.go", "source_location": "L133", "weight": 1.0}, {"source": "settings_store_add", "target": "settings_store_load", "relation": "calls", "context": "call", "confidence": "EXTRACTED", "source_file": "internal/settings/settings.go", "source_location": "L137", "weight": 1.0}, {"source": "settings_store_add", "target": "settings_store_save", "relation": "calls", "context": "call", "confidence": "EXTRACTED", "source_file": "internal/settings/settings.go", "source_location": "L151", "weight": 1.0}, {"source": "settings_store_remove", "target": "settings_store_normalize", "relation": "calls", "context": "call", "confidence": "EXTRACTED", "source_file": "internal/settings/settings.go", "source_location": "L160", "weight": 1.0}, {"source": "settings_store_remove", "target": "settings_store_load", "relation": "calls", "context": "call", "confidence": "EXTRACTED", "source_file": "internal/settings/settings.go", "source_location": "L164", "weight": 1.0}, {"source": "settings_store_remove", "target": "settings_store_save", "relation": "calls", "context": "call", "confidence": "EXTRACTED", "source_file": "internal/settings/settings.go", "source_location": "L183", "weight": 1.0}, {"source": "settings_store_normalize", "target": "settings_store_homedirectory", "relation": "calls", "context": "call", "confidence": "EXTRACTED", "source_file": "internal/settings/settings.go", "source_location": "L197", "weight": 1.0}, {"source": "settings_store_normalize", "target": "settings_store_workingdirectory", "relation": "calls", "context": "call", "confidence": "EXTRACTED", "source_file": "internal/settings/settings.go", "source_location": "L211", "weight": 1.0}, {"source": "settings_store_normalize", "target": "settings_settings_canonicalexistingdirectory", "relation": "calls", "context": "call", "confidence": "EXTRACTED", "source_file": "internal/settings/settings.go", "source_location": "L226", "weight": 1.0}, {"source": "settings_store_defaultdirectory", "target": "settings_store_homedirectory", "relation": "calls", "context": "call", "confidence": "EXTRACTED", "source_file": "internal/settings/settings.go", "source_location": "L231", "weight": 1.0}, {"source": "settings_store_defaultdirectory", "target": "settings_store_normalize", "relation": "calls", "context": "call", "confidence": "EXTRACTED", "source_file": "internal/settings/settings.go", "source_location": "L237", "weight": 1.0}, {"source": "settings_settings_contains", "target": "settings_settings_canonicalexistingdirectory", "relation": "calls", "context": "call", "confidence": "EXTRACTED", "source_file": "internal/settings/settings.go", "source_location": "L246", "weight": 1.0}, {"source": "settings_settings_contains", "target": "settings_settings_canonicalexistingpath", "relation": "calls", "context": "call", "confidence": "EXTRACTED", "source_file": "internal/settings/settings.go", "source_location": "L250", "weight": 1.0}, {"source": "settings_store_validate", "target": "settings_settings_canonicalexistingdirectory", "relation": "calls", "context": "call", "confidence": "EXTRACTED", "source_file": "internal/settings/settings.go", "source_location": "L273", "weight": 1.0}, {"source": "settings_store_canonicalize", "target": "settings_store_normalize", "relation": "calls", "context": "call", "confidence": "EXTRACTED", "source_file": "internal/settings/settings.go", "source_location": "L294", "weight": 1.0}, {"source": "settings_settings_canonicalexistingdirectory", "target": "settings_settings_canonicalexistingpath", "relation": "calls", "context": "call", "confidence": "EXTRACTED", "source_file": "internal/settings/settings.go", "source_location": "L320", "weight": 1.0}, {"source": "settings_store_configdirectory", "target": "settings_settings_configdirectory", "relation": "calls", "context": "call", "confidence": "EXTRACTED", "source_file": "internal/settings/settings.go", "source_location": "L338", "weight": 1.0}], "raw_calls": [{"caller_nid": "settings_settings_configdirectory", "callee": "UserConfigDir", "is_member_call": false, "source_file": "/Users/phranck/Developer/tools/cli/grat/internal/settings/settings.go", "source_location": "L40"}, {"caller_nid": "settings_settings_configdirectory", "callee": "Errorf", "is_member_call": false, "source_file": "/Users/phranck/Developer/tools/cli/grat/internal/settings/settings.go", "source_location": "L42"}, {"caller_nid": "settings_settings_configdirectory", "callee": "Join", "is_member_call": false, "source_file": "/Users/phranck/Developer/tools/cli/grat/internal/settings/settings.go", "source_location": "L44"}, {"caller_nid": "settings_store_path", "callee": "Join", "is_member_call": false, "source_file": "/Users/phranck/Developer/tools/cli/grat/internal/settings/settings.go", "source_location": "L53"}, {"caller_nid": "settings_store_load", "callee": "ReadFile", "is_member_call": false, "source_file": "/Users/phranck/Developer/tools/cli/grat/internal/settings/settings.go", "source_location": "L64"}, {"caller_nid": "settings_store_load", "callee": "Is", "is_member_call": false, "source_file": "/Users/phranck/Developer/tools/cli/grat/internal/settings/settings.go", "source_location": "L65"}, {"caller_nid": "settings_store_load", "callee": "Errorf", "is_member_call": false, "source_file": "/Users/phranck/Developer/tools/cli/grat/internal/settings/settings.go", "source_location": "L69"}, {"caller_nid": "settings_store_load", "callee": "Unmarshal", "is_member_call": true, "source_file": "/Users/phranck/Developer/tools/cli/grat/internal/settings/settings.go", "source_location": "L71"}, {"caller_nid": "settings_store_load", "callee": "Errorf", "is_member_call": false, "source_file": "/Users/phranck/Developer/tools/cli/grat/internal/settings/settings.go", "source_location": "L72"}, {"caller_nid": "settings_store_load", "callee": "Errorf", "is_member_call": false, "source_file": "/Users/phranck/Developer/tools/cli/grat/internal/settings/settings.go", "source_location": "L75"}, {"caller_nid": "settings_store_save", "callee": "Dir", "is_member_call": false, "source_file": "/Users/phranck/Developer/tools/cli/grat/internal/settings/settings.go", "source_location": "L94"}, {"caller_nid": "settings_store_save", "callee": "MkdirAll", "is_member_call": false, "source_file": "/Users/phranck/Developer/tools/cli/grat/internal/settings/settings.go", "source_location": "L95"}, {"caller_nid": "settings_store_save", "callee": "Errorf", "is_member_call": false, "source_file": "/Users/phranck/Developer/tools/cli/grat/internal/settings/settings.go", "source_location": "L96"}, {"caller_nid": "settings_store_save", "callee": "Chmod", "is_member_call": false, "source_file": "/Users/phranck/Developer/tools/cli/grat/internal/settings/settings.go", "source_location": "L98"}, {"caller_nid": "settings_store_save", "callee": "Errorf", "is_member_call": false, "source_file": "/Users/phranck/Developer/tools/cli/grat/internal/settings/settings.go", "source_location": "L99"}, {"caller_nid": "settings_store_save", "callee": "Marshal", "is_member_call": true, "source_file": "/Users/phranck/Developer/tools/cli/grat/internal/settings/settings.go", "source_location": "L102"}, {"caller_nid": "settings_store_save", "callee": "Errorf", "is_member_call": false, "source_file": "/Users/phranck/Developer/tools/cli/grat/internal/settings/settings.go", "source_location": "L104"}, {"caller_nid": "settings_store_save", "callee": "append", "is_member_call": false, "source_file": "/Users/phranck/Developer/tools/cli/grat/internal/settings/settings.go", "source_location": "L106"}, {"caller_nid": "settings_store_save", "callee": "TrimRight", "is_member_call": false, "source_file": "/Users/phranck/Developer/tools/cli/grat/internal/settings/settings.go", "source_location": "L106"}, {"caller_nid": "settings_store_save", "callee": "CreateTemp", "is_member_call": false, "source_file": "/Users/phranck/Developer/tools/cli/grat/internal/settings/settings.go", "source_location": "L107"}, {"caller_nid": "settings_store_save", "callee": "Errorf", "is_member_call": false, "source_file": "/Users/phranck/Developer/tools/cli/grat/internal/settings/settings.go", "source_location": "L109"}, {"caller_nid": "settings_store_save", "callee": "Name", "is_member_call": true, "source_file": "/Users/phranck/Developer/tools/cli/grat/internal/settings/settings.go", "source_location": "L111"}, {"caller_nid": "settings_store_save", "callee": "Chmod", "is_member_call": true, "source_file": "/Users/phranck/Developer/tools/cli/grat/internal/settings/settings.go", "source_location": "L113"}, {"caller_nid": "settings_store_save", "callee": "Join", "is_member_call": false, "source_file": "/Users/phranck/Developer/tools/cli/grat/internal/settings/settings.go", "source_location": "L114"}, {"caller_nid": "settings_store_save", "callee": "Errorf", "is_member_call": false, "source_file": "/Users/phranck/Developer/tools/cli/grat/internal/settings/settings.go", "source_location": "L114"}, {"caller_nid": "settings_store_save", "callee": "Close", "is_member_call": true, "source_file": "/Users/phranck/Developer/tools/cli/grat/internal/settings/settings.go", "source_location": "L114"}, {"caller_nid": "settings_store_save", "callee": "Write", "is_member_call": true, "source_file": "/Users/phranck/Developer/tools/cli/grat/internal/settings/settings.go", "source_location": "L116"}, {"caller_nid": "settings_store_save", "callee": "Join", "is_member_call": false, "source_file": "/Users/phranck/Developer/tools/cli/grat/internal/settings/settings.go", "source_location": "L117"}, {"caller_nid": "settings_store_save", "callee": "Errorf", "is_member_call": false, "source_file": "/Users/phranck/Developer/tools/cli/grat/internal/settings/settings.go", "source_location": "L117"}, {"caller_nid": "settings_store_save", "callee": "Close", "is_member_call": true, "source_file": "/Users/phranck/Developer/tools/cli/grat/internal/settings/settings.go", "source_location": "L117"}, {"caller_nid": "settings_store_save", "callee": "Sync", "is_member_call": true, "source_file": "/Users/phranck/Developer/tools/cli/grat/internal/settings/settings.go", "source_location": "L119"}, {"caller_nid": "settings_store_save", "callee": "Join", "is_member_call": false, "source_file": "/Users/phranck/Developer/tools/cli/grat/internal/settings/settings.go", "source_location": "L120"}, {"caller_nid": "settings_store_save", "callee": "Errorf", "is_member_call": false, "source_file": "/Users/phranck/Developer/tools/cli/grat/internal/settings/settings.go", "source_location": "L120"}, {"caller_nid": "settings_store_save", "callee": "Close", "is_member_call": true, "source_file": "/Users/phranck/Developer/tools/cli/grat/internal/settings/settings.go", "source_location": "L120"}, {"caller_nid": "settings_store_save", "callee": "Close", "is_member_call": true, "source_file": "/Users/phranck/Developer/tools/cli/grat/internal/settings/settings.go", "source_location": "L122"}, {"caller_nid": "settings_store_save", "callee": "Errorf", "is_member_call": false, "source_file": "/Users/phranck/Developer/tools/cli/grat/internal/settings/settings.go", "source_location": "L123"}, {"caller_nid": "settings_store_save", "callee": "Errorf", "is_member_call": false, "source_file": "/Users/phranck/Developer/tools/cli/grat/internal/settings/settings.go", "source_location": "L126"}, {"caller_nid": "settings_store_add", "callee": "append", "is_member_call": false, "source_file": "/Users/phranck/Developer/tools/cli/grat/internal/settings/settings.go", "source_location": "L149"}, {"caller_nid": "settings_store_add", "callee": "Strings", "is_member_call": false, "source_file": "/Users/phranck/Developer/tools/cli/grat/internal/settings/settings.go", "source_location": "L150"}, {"caller_nid": "settings_store_remove", "callee": "make", "is_member_call": false, "source_file": "/Users/phranck/Developer/tools/cli/grat/internal/settings/settings.go", "source_location": "L171"}, {"caller_nid": "settings_store_remove", "callee": "append", "is_member_call": false, "source_file": "/Users/phranck/Developer/tools/cli/grat/internal/settings/settings.go", "source_location": "L177"}, {"caller_nid": "settings_store_normalize", "callee": "TrimSpace", "is_member_call": false, "source_file": "/Users/phranck/Developer/tools/cli/grat/internal/settings/settings.go", "source_location": "L192"}, {"caller_nid": "settings_store_normalize", "callee": "New", "is_member_call": false, "source_file": "/Users/phranck/Developer/tools/cli/grat/internal/settings/settings.go", "source_location": "L194"}, {"caller_nid": "settings_store_normalize", "callee": "HasPrefix", "is_member_call": false, "source_file": "/Users/phranck/Developer/tools/cli/grat/internal/settings/settings.go", "source_location": "L196"}, {"caller_nid": "settings_store_normalize", "callee": "Join", "is_member_call": false, "source_file": "/Users/phranck/Developer/tools/cli/grat/internal/settings/settings.go", "source_location": "L204"}, {"caller_nid": "settings_store_normalize", "callee": "TrimPrefix", "is_member_call": false, "source_file": "/Users/phranck/Developer/tools/cli/grat/internal/settings/settings.go", "source_location": "L204"}, {"caller_nid": "settings_store_normalize", "callee": "IsAbs", "is_member_call": false, "source_file": "/Users/phranck/Developer/tools/cli/grat/internal/settings/settings.go", "source_location": "L207"}, {"caller_nid": "settings_store_normalize", "callee": "TrimSpace", "is_member_call": false, "source_file": "/Users/phranck/Developer/tools/cli/grat/internal/settings/settings.go", "source_location": "L209"}, {"caller_nid": "settings_store_normalize", "callee": "Join", "is_member_call": false, "source_file": "/Users/phranck/Developer/tools/cli/grat/internal/settings/settings.go", "source_location": "L216"}, {"caller_nid": "settings_store_normalize", "callee": "Abs", "is_member_call": false, "source_file": "/Users/phranck/Developer/tools/cli/grat/internal/settings/settings.go", "source_location": "L218"}, {"caller_nid": "settings_store_normalize", "callee": "Errorf", "is_member_call": false, "source_file": "/Users/phranck/Developer/tools/cli/grat/internal/settings/settings.go", "source_location": "L220"}, {"caller_nid": "settings_store_normalize", "callee": "EvalSymlinks", "is_member_call": false, "source_file": "/Users/phranck/Developer/tools/cli/grat/internal/settings/settings.go", "source_location": "L222"}, {"caller_nid": "settings_store_normalize", "callee": "Clean", "is_member_call": false, "source_file": "/Users/phranck/Developer/tools/cli/grat/internal/settings/settings.go", "source_location": "L222"}, {"caller_nid": "settings_store_normalize", "callee": "Errorf", "is_member_call": false, "source_file": "/Users/phranck/Developer/tools/cli/grat/internal/settings/settings.go", "source_location": "L224"}, {"caller_nid": "settings_store_defaultdirectory", "callee": "Join", "is_member_call": false, "source_file": "/Users/phranck/Developer/tools/cli/grat/internal/settings/settings.go", "source_location": "L235"}, {"caller_nid": "settings_store_defaultdirectory", "callee": "Stat", "is_member_call": false, "source_file": "/Users/phranck/Developer/tools/cli/grat/internal/settings/settings.go", "source_location": "L236"}, {"caller_nid": "settings_store_defaultdirectory", "callee": "IsDir", "is_member_call": true, "source_file": "/Users/phranck/Developer/tools/cli/grat/internal/settings/settings.go", "source_location": "L236"}, {"caller_nid": "settings_store_defaultdirectory", "callee": "Is", "is_member_call": false, "source_file": "/Users/phranck/Developer/tools/cli/grat/internal/settings/settings.go", "source_location": "L238"}, {"caller_nid": "settings_store_defaultdirectory", "callee": "Errorf", "is_member_call": false, "source_file": "/Users/phranck/Developer/tools/cli/grat/internal/settings/settings.go", "source_location": "L239"}, {"caller_nid": "settings_settings_contains", "callee": "Errorf", "is_member_call": false, "source_file": "/Users/phranck/Developer/tools/cli/grat/internal/settings/settings.go", "source_location": "L248"}, {"caller_nid": "settings_settings_contains", "callee": "Errorf", "is_member_call": false, "source_file": "/Users/phranck/Developer/tools/cli/grat/internal/settings/settings.go", "source_location": "L252"}, {"caller_nid": "settings_settings_contains", "callee": "Rel", "is_member_call": false, "source_file": "/Users/phranck/Developer/tools/cli/grat/internal/settings/settings.go", "source_location": "L254"}, {"caller_nid": "settings_settings_contains", "callee": "Errorf", "is_member_call": false, "source_file": "/Users/phranck/Developer/tools/cli/grat/internal/settings/settings.go", "source_location": "L256"}, {"caller_nid": "settings_settings_contains", "callee": "HasPrefix", "is_member_call": false, "source_file": "/Users/phranck/Developer/tools/cli/grat/internal/settings/settings.go", "source_location": "L258"}, {"caller_nid": "settings_settings_contains", "callee": "string", "is_member_call": false, "source_file": "/Users/phranck/Developer/tools/cli/grat/internal/settings/settings.go", "source_location": "L258"}, {"caller_nid": "settings_store_validate", "callee": "Errorf", "is_member_call": false, "source_file": "/Users/phranck/Developer/tools/cli/grat/internal/settings/settings.go", "source_location": "L263"}, {"caller_nid": "settings_store_validate", "callee": "make", "is_member_call": false, "source_file": "/Users/phranck/Developer/tools/cli/grat/internal/settings/settings.go", "source_location": "L265"}, {"caller_nid": "settings_store_validate", "callee": "TrimSpace", "is_member_call": false, "source_file": "/Users/phranck/Developer/tools/cli/grat/internal/settings/settings.go", "source_location": "L267"}, {"caller_nid": "settings_store_validate", "callee": "New", "is_member_call": false, "source_file": "/Users/phranck/Developer/tools/cli/grat/internal/settings/settings.go", "source_location": "L268"}, {"caller_nid": "settings_store_validate", "callee": "IsAbs", "is_member_call": false, "source_file": "/Users/phranck/Developer/tools/cli/grat/internal/settings/settings.go", "source_location": "L270"}, {"caller_nid": "settings_store_validate", "callee": "Errorf", "is_member_call": false, "source_file": "/Users/phranck/Developer/tools/cli/grat/internal/settings/settings.go", "source_location": "L271"}, {"caller_nid": "settings_store_validate", "callee": "Errorf", "is_member_call": false, "source_file": "/Users/phranck/Developer/tools/cli/grat/internal/settings/settings.go", "source_location": "L275"}, {"caller_nid": "settings_store_validate", "callee": "Errorf", "is_member_call": false, "source_file": "/Users/phranck/Developer/tools/cli/grat/internal/settings/settings.go", "source_location": "L278"}, {"caller_nid": "settings_store_validate", "callee": "Errorf", "is_member_call": false, "source_file": "/Users/phranck/Developer/tools/cli/grat/internal/settings/settings.go", "source_location": "L281"}, {"caller_nid": "settings_store_canonicalize", "callee": "Errorf", "is_member_call": false, "source_file": "/Users/phranck/Developer/tools/cli/grat/internal/settings/settings.go", "source_location": "L290"}, {"caller_nid": "settings_store_canonicalize", "callee": "make", "is_member_call": false, "source_file": "/Users/phranck/Developer/tools/cli/grat/internal/settings/settings.go", "source_location": "L292"}, {"caller_nid": "settings_store_canonicalize", "callee": "append", "is_member_call": false, "source_file": "/Users/phranck/Developer/tools/cli/grat/internal/settings/settings.go", "source_location": "L298"}, {"caller_nid": "settings_store_canonicalize", "callee": "Strings", "is_member_call": false, "source_file": "/Users/phranck/Developer/tools/cli/grat/internal/settings/settings.go", "source_location": "L300"}, {"caller_nid": "settings_settings_canonicalexistingpath", "callee": "Abs", "is_member_call": false, "source_file": "/Users/phranck/Developer/tools/cli/grat/internal/settings/settings.go", "source_location": "L305"}, {"caller_nid": "settings_settings_canonicalexistingpath", "callee": "EvalSymlinks", "is_member_call": false, "source_file": "/Users/phranck/Developer/tools/cli/grat/internal/settings/settings.go", "source_location": "L309"}, {"caller_nid": "settings_settings_canonicalexistingpath", "callee": "Clean", "is_member_call": false, "source_file": "/Users/phranck/Developer/tools/cli/grat/internal/settings/settings.go", "source_location": "L309"}, {"caller_nid": "settings_settings_canonicalexistingpath", "callee": "Stat", "is_member_call": false, "source_file": "/Users/phranck/Developer/tools/cli/grat/internal/settings/settings.go", "source_location": "L313"}, {"caller_nid": "settings_settings_canonicalexistingdirectory", "callee": "Errorf", "is_member_call": false, "source_file": "/Users/phranck/Developer/tools/cli/grat/internal/settings/settings.go", "source_location": "L322"}, {"caller_nid": "settings_settings_canonicalexistingdirectory", "callee": "Stat", "is_member_call": false, "source_file": "/Users/phranck/Developer/tools/cli/grat/internal/settings/settings.go", "source_location": "L324"}, {"caller_nid": "settings_settings_canonicalexistingdirectory", "callee": "IsDir", "is_member_call": true, "source_file": "/Users/phranck/Developer/tools/cli/grat/internal/settings/settings.go", "source_location": "L328"}, {"caller_nid": "settings_settings_canonicalexistingdirectory", "callee": "Errorf", "is_member_call": false, "source_file": "/Users/phranck/Developer/tools/cli/grat/internal/settings/settings.go", "source_location": "L329"}, {"caller_nid": "settings_store_configdirectory", "callee": "ConfigDir", "is_member_call": true, "source_file": "/Users/phranck/Developer/tools/cli/grat/internal/settings/settings.go", "source_location": "L336"}, {"caller_nid": "settings_store_homedirectory", "callee": "HomeDir", "is_member_call": true, "source_file": "/Users/phranck/Developer/tools/cli/grat/internal/settings/settings.go", "source_location": "L343"}, {"caller_nid": "settings_store_homedirectory", "callee": "UserHomeDir", "is_member_call": false, "source_file": "/Users/phranck/Developer/tools/cli/grat/internal/settings/settings.go", "source_location": "L345"}, {"caller_nid": "settings_store_homedirectory", "callee": "Errorf", "is_member_call": false, "source_file": "/Users/phranck/Developer/tools/cli/grat/internal/settings/settings.go", "source_location": "L347"}, {"caller_nid": "settings_store_workingdirectory", "callee": "Getwd", "is_member_call": true, "source_file": "/Users/phranck/Developer/tools/cli/grat/internal/settings/settings.go", "source_location": "L354"}, {"caller_nid": "settings_store_workingdirectory", "callee": "Getwd", "is_member_call": false, "source_file": "/Users/phranck/Developer/tools/cli/grat/internal/settings/settings.go", "source_location": "L356"}, {"caller_nid": "settings_store_workingdirectory", "callee": "Errorf", "is_member_call": false, "source_file": "/Users/phranck/Developer/tools/cli/grat/internal/settings/settings.go", "source_location": "L358"}, {"caller_nid": "settings_store_rename", "callee": "Rename", "is_member_call": true, "source_file": "/Users/phranck/Developer/tools/cli/grat/internal/settings/settings.go", "source_location": "L365"}, {"caller_nid": "settings_store_rename", "callee": "Rename", "is_member_call": false, "source_file": "/Users/phranck/Developer/tools/cli/grat/internal/settings/settings.go", "source_location": "L367"}]}