{"nodes": [{"id": "users_phranck_developer_tools_cli_grat_internal_runtime_progress_go", "label": "progress.go", "file_type": "code", "source_file": "internal/runtime/progress.go", "source_location": "L1"}, {"id": "runtime_progressstage", "label": "ProgressStage", "file_type": "code", "source_file": "internal/runtime/progress.go", "source_location": "L7"}, {"id": "runtime_progressevent", "label": "ProgressEvent", "file_type": "code", "source_file": "internal/runtime/progress.go", "source_location": "L32"}, {"id": "service", "label": "Service", "file_type": "code", "source_file": "internal/runtime/progress.go", "source_location": "L33"}, {"id": "runtime_progressobserver", "label": "ProgressObserver", "file_type": "code", "source_file": "internal/runtime/progress.go", "source_location": "L39"}, {"id": "runtime_progressobserverfunc", "label": "ProgressObserverFunc", "file_type": "code", "source_file": "internal/runtime/progress.go", "source_location": "L44"}, {"id": "runtime_progressobserverfunc_observeprogress", "label": ".ObserveProgress()", "file_type": "code", "source_file": "internal/runtime/progress.go", "source_location": "L47"}, {"id": "runtime_manager", "label": "Manager", "file_type": "code", "source_file": "internal/runtime/progress.go", "source_location": "L51"}, {"id": "runtime_manager_report", "label": ".report()", "file_type": "code", "source_file": "internal/runtime/progress.go", "source_location": "L51"}], "edges": [{"source": "users_phranck_developer_tools_cli_grat_internal_runtime_progress_go", "target": "go_pkg_github_com_phranck_grat_internal_config", "relation": "imports_from", "confidence": "EXTRACTED", "source_file": "internal/runtime/progress.go", "source_location": "L3", "weight": 1.0, "context": "import"}, {"source": "users_phranck_developer_tools_cli_grat_internal_runtime_progress_go", "target": "runtime_progressstage", "relation": "contains", "confidence": "EXTRACTED", "source_file": "internal/runtime/progress.go", "source_location": "L7", "weight": 1.0}, {"source": "users_phranck_developer_tools_cli_grat_internal_runtime_progress_go", "target": "runtime_progressevent", "relation": "contains", "confidence": "EXTRACTED", "source_file": "internal/runtime/progress.go", "source_location": "L32", "weight": 1.0}, {"source": "runtime_progressevent", "target": "service", "relation": "references", "confidence": "EXTRACTED", "source_file": "internal/runtime/progress.go", "source_location": "L33", "weight": 1.0, "context": "field"}, {"source": "runtime_progressevent", "target": "runtime_progressstage", "relation": "references", "confidence": "EXTRACTED", "source_file": "internal/runtime/progress.go", "source_location": "L34", "weight": 1.0, "context": "field"}, {"source": "users_phranck_developer_tools_cli_grat_internal_runtime_progress_go", "target": "runtime_progressobserver", "relation": "contains", "confidence": "EXTRACTED", "source_file": "internal/runtime/progress.go", "source_location": "L39", "weight": 1.0}, {"source": "users_phranck_developer_tools_cli_grat_internal_runtime_progress_go", "target": "runtime_progressobserverfunc", "relation": "contains", "confidence": "EXTRACTED", "source_file": "internal/runtime/progress.go", "source_location": "L44", "weight": 1.0}, {"source": "runtime_progressobserverfunc", "target": "runtime_progressobserverfunc_observeprogress", "relation": "method", "confidence": "EXTRACTED", "source_file": "internal/runtime/progress.go", "source_location": "L47", "weight": 1.0}, {"source": "runtime_progressobserverfunc_observeprogress", "target": "runtime_progressevent", "relation": "references", "confidence": "EXTRACTED", "source_file": "internal/runtime/progress.go", "source_location": "L47", "weight": 1.0, "context": "parameter_type"}, {"source": "runtime_manager", "target": "runtime_manager_report", "relation": "method", "confidence": "EXTRACTED", "source_file": "internal/runtime/progress.go", "source_location": "L51", "weight": 1.0}, {"source": "runtime_manager_report", "target": "service", "relation": "references", "confidence": "EXTRACTED", "source_file": "internal/runtime/progress.go", "source_location": "L51", "weight": 1.0, "context": "parameter_type"}, {"source": "runtime_manager_report", "target": "runtime_progressstage", "relation": "references", "confidence": "EXTRACTED", "source_file": "internal/runtime/progress.go", "source_location": "L51", "weight": 1.0, "context": "parameter_type"}, {"source": "runtime_manager_report", "target": "runtime_progressobserverfunc_observeprogress", "relation": "calls", "context": "call", "confidence": "EXTRACTED", "source_file": "internal/runtime/progress.go", "source_location": "L53", "weight": 1.0}], "raw_calls": [{"caller_nid": "runtime_progressobserverfunc_observeprogress", "callee": "function", "is_member_call": false, "source_file": "/Users/phranck/Developer/tools/cli/grat/internal/runtime/progress.go", "source_location": "L48"}]}